chalk_rip/__init__.py
chalk_rip/chalk.py
uc_chalk_rip-0.6.dist-info/DESCRIPTION.rst
uc_chalk_rip-0.6.dist-info/METADATA
uc_chalk_rip-0.6.dist-info/RECORD
uc_chalk_rip-0.6.dist-info/WHEEL
uc_chalk_rip-0.6.dist-info/entry_points.txt
uc_chalk_rip-0.6.dist-info/metadata.json
uc_chalk_rip-0.6.dist-info/top_level.txt
