Metadata-Version: 2.0
Name: uc-chalk-rip
Version: 0.6
Summary: Ripper for Uchicago's chalk site
Home-page: https://github.com/reidmcy/uc_chalk_rip
Author: Reid McIlroy-Young
Author-email: reidmcy@uchicago.edu
License: GPL
Download-URL: https://github.com/reidmcy/uc_chalk_rip/archive/0.6.tar.gz
Platform: UNKNOWN
Classifier: Programming Language :: Python :: 3 :: Only
Classifier: Development Status :: 4 - Beta
Requires-Dist: bs4
Requires-Dist: requests
